TextVault/HillCipherWithNumbers.py
TextVault/JMatrix.py
TextVault/__init__.py
TextVault/base_class.py
TextVault/knapsack.py
TextVault/rsa.py
TextVault/vigenere.py
textvault-1.0.2.dist-info/METADATA
textvault-1.0.2.dist-info/WHEEL
textvault-1.0.2.dist-info/licenses/LICENSE
textvault-1.0.2.dist-info/RECORD
